vsbio/__init__.py
vsbio/fastq_quality.py
vsbio-0.1.0.dist-info/LICENSE
vsbio-0.1.0.dist-info/METADATA
vsbio-0.1.0.dist-info/WHEEL
vsbio-0.1.0.dist-info/top_level.txt
vsbio-0.1.0.dist-info/RECORD
