Metadata-Version: 2.1
Name: vsbio
Version: 0.1.0
Summary: Collection of simple bioinformatic tools.
Home-page: https://github.com/USDA-VS/vsbio
Author: Tod Stuber
Author-email: tod.p.stuber@usda.gov
License: UNKNOWN
Platform: UNKNOWN
Classifier: Programming Language :: Python :: 3
Classifier: License :: OSI Approved :: MIT License
Classifier: Operating System :: OS Independent
